examples/__init__.py
examples/payment_example_request.py
examples/payment_example_verify.py
tests/__init__.py
tests/test_client.py
zibal_payment/__init__.py
zibal_payment/client.py
zibal_payment/exceptions.py
zibal_payment-1.0.2.dist-info/LICENSE
zibal_payment-1.0.2.dist-info/METADATA
zibal_payment-1.0.2.dist-info/WHEEL
zibal_payment-1.0.2.dist-info/top_level.txt
zibal_payment-1.0.2.dist-info/RECORD
