Metadata-Version: 2.1
Name: zibal_payment
Version: 1.0.2
Summary: A simple and secure Python package for integrating online payment processing in Django projects.
Home-page: https://github.com/Mohammad222PR/zibal_payment
Author: Mohammad Eslami
Keywords: payment gateway django integration online payments
Classifier: Programming Language :: Python :: 3
Classifier: License :: OSI Approved :: MIT License
Classifier: Operating System :: OS Independent
Classifier: Development Status :: 3 - Alpha
Classifier: Intended Audience :: Developers
Classifier: Topic :: Software Development :: Libraries :: Python Modules
Requires-Python: >=3.6
License-File: LICENSE
Requires-Dist: requests >=2.25.0
